rrt/__init__.py
rrt/dubins.py
rrt/dynamic_environment.py
rrt/environment.py
rrt/obstacle.py
rrt/rrt.py
rrt-0.1.1.dist-info/LICENSE
rrt-0.1.1.dist-info/METADATA
rrt-0.1.1.dist-info/WHEEL
rrt-0.1.1.dist-info/RECORD
