Metadata-Version: 2.1
Name: rrt
Version: 0.1.1
Summary: Simple implementation of a Rapidly Exploring Random Tree using Dubins path as an expansion method
License: MIT
Author: FelicienC
Author-email: cantalloubef@gmail.com
Requires-Python: >=3.9,<4.0
Classifier: License :: OSI Approved :: MIT License
Classifier: Programming Language :: Python :: 3
Classifier: Programming Language :: Python :: 3.9
Classifier: Programming Language :: Python :: 3.10
Classifier: Programming Language :: Python :: 3.11
Requires-Dist: matplotlib (>=3.8.3,<4.0.0)
Requires-Dist: numpy (>=1.26.4,<2.0.0)
Requires-Dist: scipy (>=1.12.0,<2.0.0)
Requires-Dist: shapely (>=2.0.3,<3.0.0)
